journalist/__init__.py
journalist/config.py
journalist/core/__init__.py
journalist/core/browserless_client.py
journalist/core/config.py
journalist/core/content_extractor.py
journalist/core/file_manager.py
journalist/core/link_discoverer.py
journalist/core/network_utils.py
journalist/core/session_manager.py
journalist/core/utils.py
journalist/core/web_scraper.py
journalist/exceptions.py
journalist/extractors/__init__.py
journalist/extractors/base_extractor.py
journalist/extractors/fullpage_extractor.py
journalist/extractors/ldjson_extractor.py
journalist/extractors/readability_extractor.py
journalist/extractors/selector_extractor.py
journalist/journalist.py
journ4list-0.13.0.dist-info/METADATA
journ4list-0.13.0.dist-info/WHEEL
journ4list-0.13.0.dist-info/licenses/LICENSE
journ4list-0.13.0.dist-info/RECORD
