Metadata-Version: 2.4
Name: journ4list
Version: 0.13.0
Summary: A powerful async news content extraction library with modern API for web scraping and article analysis
License: MIT
License-File: LICENSE
Keywords: scraping,news,content,extraction,journalism,articles,web-scraping
Author: Oktay Burak Ertas
Author-email: oktay.burak.ertas@gmail.com
Maintainer: Oktay Burak Ertas
Maintainer-email: oktay.burak.ertas@gmail.com
Requires-Python: >=3.8
Classifier: Development Status :: 4 - Beta
Classifier: Intended Audience :: Developers
Classifier: Intended Audience :: Information Technology
Classifier: License :: OSI Approved :: MIT License
Classifier: Operating System :: OS Independent
Classifier: Programming Language :: Python
Classifier: Programming Language :: Python :: 3
Classifier: Programming Language :: Python :: 3.8
Classifier: Programming Language :: Python :: 3.9
Classifier: Programming Language :: Python :: 3.10
Classifier: Programming Language :: Python :: 3.11
Classifier: Programming Language :: Python :: 3.12
Classifier: Programming Language :: Python :: 3.13
Classifier: Programming Language :: Python :: 3.14
Classifier: Topic :: Internet :: WWW/HTTP :: Dynamic Content :: News/Diary
Classifier: Topic :: Software Development :: Libraries :: Python Modules
Classifier: Topic :: Text Processing :: Markup :: HTML
Provides-Extra: all
Provides-Extra: newspaper
Requires-Dist: aiohttp (>=3.9.0,<4.0.0)
Requires-Dist: beautifulsoup4 (>=4.13.0,<5.0.0)
Requires-Dist: datefinder (>=0.7.3,<0.8.0)
Requires-Dist: lxml (>=4.9.0,<5.0.0)
Requires-Dist: newspaper3k (>=0.2.8,<0.3.0) ; extra == "newspaper" or extra == "all"
Requires-Dist: readability-lxml (>=0.8.1,<0.9.0)
Requires-Dist: requests (>=2.31.0,<3.0.0)
Requires-Dist: werkzeug (>=3.0.0,<4.0.0)
Project-URL: Documentation, https://journalist.readthedocs.io
Project-URL: Homepage, https://github.com/username/journalist
Project-URL: Repository, https://github.com/username/journalist
